{
    "updateInstructions":
    {
        "general":
        [
            {
            "type":"A=sumbC::NB",
            "parameters":{
                "name":"Ex_2_0_y1_e_Ex_u_IP1",
                "A":"E",
                "neighborGrid":"grid_uu",
                "A_direction":"x",
                "A_indStart":[2, "_gb_ny_", 0],
                "A_indEnd":["_gb_nx_m1_", "_gb_ny_p1_", "_gb_nz_p1_"],
                "b":[0.25, 0.75],
                "C":["E", "E"],
                "C_direction":["x", "x"],
                "C_indStart":[[0, 0, "_gll_nz_"], [1, 0, "_gll_nz_"]],
                "A_stride":[2, 1, 2]
                }
            },
            {
            "type":"A=sumbC::NB",
            "parameters":{
                "name":"Ex_2_1_y1_e_Ex_u_IP1",
                "A":"E",
                "neighborGrid":"grid_uu",
                "A_direction":"x",
                "A_indStart":[1, "_gb_ny_", 0],
                "A_indEnd":["_gb_nx_", "_gb_ny_p1_", "_gb_nz_p1_"],
                "b":[0.75, 0.25],
                "C":["E", "E"],
                "C_direction":["x", "x"],
                "C_indStart":[[0, 0, "_gll_nz_"], [1, 0, "_gll_nz_"]],
                "A_stride":[2, 1, 2]
                }
            },
            {
            "type":"A=sumbC",
            "parameters":{
                "name":"Ex_1_y1_e_Ex_2_avg_IP1",
                "A":"E",
                "A_direction":"x",
                "A_indStart":[0, "_gb_ny_", 1],
                "A_indEnd":["_gb_nx_", "_gb_ny_p1_", "_gb_nz_"],
                "b":[0.5, 0.5],
                "C":["E", "E"],
                "C_direction":["x", "x"],
                "C_indStart":[[0, "_gb_ny_", 0], [0, "_gb_ny_", 2]],
                "A_stride":[1, 1, 2],
                "C_stride":[[1, 1, 2], [1, 1, 2]]
                }
            },
            {
            "type":"A=sumbC::NB",
            "parameters":{
                "name":"Ez_2_0_y1_e_Ez_u_IP1",
                "A":"E",
                "neighborGrid":"grid_uu",
                "A_direction":"z",
                "A_indStart":[0, "_gb_ny_", 0],
                "A_indEnd":["_gb_nx_p1_", "_gb_ny_p1_", "_gb_nz_m1_"],
                "b":[0.25, 0.75],
                "C":["E", "E"],
                "C_direction":["z", "z"],
                "C_indStart":[[0, 0, "_gll_nz_m1_"], [0, 0, "_gll_nz_"]],
                "A_stride":[2, 1, 2]
                }
            },
            {
            "type":"A=sumbC::NB",
            "parameters":{
                "name":"Ez_2_1_y1_e_Ez_u_IP1",
                "A":"E",
                "neighborGrid":"grid_uu",
                "A_direction":"z",
                "A_indStart":[0, "_gb_ny_", 1],
                "A_indEnd":["_gb_nx_p1_", "_gb_ny_p1_", "_gb_nz_"],
                "b":[0.75, 0.25],
                "C":["E", "E"],
                "C_direction":["z", "z"],
                "C_indStart":[[0, 0, "_gll_nz_"], [0, 0, "_gll_nz_p1_"]],
                "A_stride":[2, 1, 2]
                }
            },
            {
            "type":"A=sumbC",
            "parameters":{
                "name":"Ez_1_y1_e_Ez_2_avg_IP1",
                "A":"E",
                "A_direction":"z",
                "A_indStart":[1, "_gb_ny_", 0],
                "A_indEnd":["_gb_nx_", "_gb_ny_p1_", "_gb_nz_"],
                "b":[0.5, 0.5],
                "C":["E", "E"],
                "C_direction":["z", "z"],
                "C_indStart":[[0, "_gb_ny_", 0], [2, "_gb_ny_", 0]],
                "A_stride":[2, 1, 1],
                "C_stride":[[2, 1, 1], [2, 1, 1]]
                }
            }
        ],
        "up_only":
        [
            {
            "type":"A=sumbC::NB",
            "parameters":{
                "name":"Ex_2_0_y1x0_e_Ex_u_IP0",
                "A":"E",
                "neighborGrid":"grid_uu",
                "A_direction":"x",
                "A_indStart":[0, "_gb_ny_", 0],
                "A_indEnd":[1, "_gb_ny_p1_", "_gb_nz_p1_"],
                "b":[1.0],
                "C":["E"],
                "C_direction":["x"],
                "C_indStart":[[0, 0, "_gll_nz_"]],
                "A_stride":[2, 1, 2]
                }
            }
        ],
        "up_back":
        [
            {
            "type":"A=sumbC::NB",
            "parameters":{
                "name":"Ex_2_0_y1x0_e_Ex_u_IP1",
                "A":"E",
                "neighborGrid":"grid_uu",
                "A_direction":"x",
                "A_indStart":[0, "_gb_ny_", 0],
                "A_indEnd":[1, "_gb_ny_p1_", "_gb_nz_p1_"],
                "b":[0.75],
                "C":["E"],
                "C_direction":["x"],
                "C_indStart":[[0, 0, "_gll_nz_"]],
                "A_stride":[2, 1, 2]
                }
            },
            {
            "type":"A+=sumbC::NB",
            "parameters":{
                "name":"Ex_2_0_y1x0_pe_Ex_b_IP1",
                "A":"E",
                "neighborGrid":"grid_bb",
                "A_direction":"x",
                "A_indStart":[0, "_gb_ny_", 0],
                "A_indEnd":[1, "_gb_ny_p1_", "_gb_nz_p1_"],
                "b":[0.25],
                "C":["E"],
                "C_direction":["x"],
                "C_indStart":[["_gbb_nx_m1_", "_gdd_ny_p_gf_ny2_", "_gll_nz_"]],
                "A_stride":[2, 1, 2]
                }
            }
        ]
    },
    "updateSequences":
    [
        {"name":"interpolate_E_edge_IP1_02",
        "sequence":{
            "general":
            [
                "Ex_2_0_y1_e_Ex_u_IP1",
                "Ex_2_1_y1_e_Ex_u_IP1",
                "Ez_2_0_y1_e_Ez_u_IP1",
                "Ez_2_1_y1_e_Ez_u_IP1"
            ],
            "up_only":
            [
                "Ex_2_0_y1x0_e_Ex_u_IP0"
            ],
            "up_back":
            [
                "Ex_2_0_y1x0_e_Ex_u_IP1",
                "Ex_2_0_y1x0_pe_Ex_b_IP1"
            ]
        }
        },
        {"name":"interpolate_E_edge_IP1_1",
        "sequence":{
            "general":
            [
                "Ex_1_y1_e_Ex_2_avg_IP1",
                "Ez_1_y1_e_Ez_2_avg_IP1"
            ],
            "up_only":
            [
            ],
            "up_back":
            [
            ]
        }
        }
    ]
}
